ansible_aap_api_client/__init__.py
ansible_aap_api_client/ansible_aap_api_client_cli.py
ansible_aap_api_client/base_connection.py
ansible_aap_api_client/groups.py
ansible_aap_api_client/hosts.py
ansible_aap_api_client/inventories.py
ansible_aap_api_client/inventory_management.py
ansible_aap_api_client/job_management.py
ansible_aap_api_client/job_templates.py
ansible_aap_api_client/jobs.py
ansible_aap_api_client/organizations.py
ansible_aap_api_client/schemas.py
ansible_aap_api_client/version.py
ansible_aap_api_client/interfaces/__init__.py
ansible_aap_api_client/interfaces/runable.py
ansible_aap_api_client-0.1.3.dist-info/licenses/LICENSE
ansible_aap_api_client-0.1.3.dist-info/METADATA
ansible_aap_api_client-0.1.3.dist-info/WHEEL
ansible_aap_api_client-0.1.3.dist-info/entry_points.txt
ansible_aap_api_client-0.1.3.dist-info/top_level.txt
ansible_aap_api_client-0.1.3.dist-info/RECORD
